{"nodes": [{"id": "gateway_src_db_repositories_notification_ts", "label": "notification.ts", "file_type": "code", "source_file": "gateway\\src\\db\\repositories\\notification.ts", "source_location": "L1"}, {"id": "notification_findbydevice", "label": "findByDevice()", "file_type": "code", "source_file": "gateway\\src\\db\\repositories\\notification.ts", "source_location": "L31"}, {"id": "notification_findbyuser", "label": "findByUser()", "file_type": "code", "source_file": "gateway\\src\\db\\repositories\\notification.ts", "source_location": "L39"}, {"id": "notification_countunread", "label": "countUnread()", "file_type": "code", "source_file": "gateway\\src\\db\\repositories\\notification.ts", "source_location": "L47"}, {"id": "notification_countunreadbyuser", "label": "countUnreadByUser()", "file_type": "code", "source_file": "gateway\\src\\db\\repositories\\notification.ts", "source_location": "L56"}, {"id": "notification_hastodaynotification", "label": "hasTodayNotification()", "file_type": "code", "source_file": "gateway\\src\\db\\repositories\\notification.ts", "source_location": "L65"}, {"id": "notification_create", "label": "create()", "file_type": "code", "source_file": "gateway\\src\\db\\repositories\\notification.ts", "source_location": "L87"}, {"id": "notification_markread", "label": "markRead()", "file_type": "code", "source_file": "gateway\\src\\db\\repositories\\notification.ts", "source_location": "L104"}, {"id": "notification_markallread", "label": "markAllRead()", "file_type": "code", "source_file": "gateway\\src\\db\\repositories\\notification.ts", "source_location": "L109"}, {"id": "notification_markallreadbyuser", "label": "markAllReadByUser()", "file_type": "code", "source_file": "gateway\\src\\db\\repositories\\notification.ts", "source_location": "L117"}], "edges": [{"source": "gateway_src_db_repositories_notification_ts", "target": "gateway_src_db_repositories_pool_ts", "relation": "imports_from", "confidence": "EXTRACTED", "source_file": "gateway\\src\\db\\repositories\\notification.ts", "source_location": "L5", "weight": 1.0}, {"source": "gateway_src_db_repositories_notification_ts", "target": "notification_findbydevice", "relation": "contains", "confidence": "EXTRACTED", "source_file": "gateway\\src\\db\\repositories\\notification.ts", "source_location": "L31", "weight": 1.0}, {"source": "gateway_src_db_repositories_notification_ts", "target": "notification_findbyuser", "relation": "contains", "confidence": "EXTRACTED", "source_file": "gateway\\src\\db\\repositories\\notification.ts", "source_location": "L39", "weight": 1.0}, {"source": "gateway_src_db_repositories_notification_ts", "target": "notification_countunread", "relation": "contains", "confidence": "EXTRACTED", "source_file": "gateway\\src\\db\\repositories\\notification.ts", "source_location": "L47", "weight": 1.0}, {"source": "gateway_src_db_repositories_notification_ts", "target": "notification_countunreadbyuser", "relation": "contains", "confidence": "EXTRACTED", "source_file": "gateway\\src\\db\\repositories\\notification.ts", "source_location": "L56", "weight": 1.0}, {"source": "gateway_src_db_repositories_notification_ts", "target": "notification_hastodaynotification", "relation": "contains", "confidence": "EXTRACTED", "source_file": "gateway\\src\\db\\repositories\\notification.ts", "source_location": "L65", "weight": 1.0}, {"source": "gateway_src_db_repositories_notification_ts", "target": "notification_create", "relation": "contains", "confidence": "EXTRACTED", "source_file": "gateway\\src\\db\\repositories\\notification.ts", "source_location": "L87", "weight": 1.0}, {"source": "gateway_src_db_repositories_notification_ts", "target": "notification_markread", "relation": "contains", "confidence": "EXTRACTED", "source_file": "gateway\\src\\db\\repositories\\notification.ts", "source_location": "L104", "weight": 1.0}, {"source": "gateway_src_db_repositories_notification_ts", "target": "notification_markallread", "relation": "contains", "confidence": "EXTRACTED", "source_file": "gateway\\src\\db\\repositories\\notification.ts", "source_location": "L109", "weight": 1.0}, {"source": "gateway_src_db_repositories_notification_ts", "target": "notification_markallreadbyuser", "relation": "contains", "confidence": "EXTRACTED", "source_file": "gateway\\src\\db\\repositories\\notification.ts", "source_location": "L117", "weight": 1.0}]}